Metadata-Version: 2.1
Name: midi-beeper
Version: 1.79.1
Summary: Play MIDI files using piezo beepers and other sounders
Home-page: http://ssb22.user.srcf.net/mwrhome/midi-beeper.html
Author: Silas S. Brown
Author-email: ssb22@cam.ac.uk
License: Apache 2
Platform: all
Classifier: Programming Language :: Python :: 2
Classifier: Programming Language :: Python :: 3
Classifier: License :: OSI Approved :: Apache Software License
Classifier: Operating System :: OS Independent
Requires-Python: >=2.2
License-File: LICENSE
